acky/__init__.py
acky/api.py
acky/aws.py
acky/ec2.py
acky/iam.py
acky/rds.py
acky/s3.py
acky/sqs.py
acky/sts.py
acky-0.2.3.dist-info/DESCRIPTION.rst
acky-0.2.3.dist-info/METADATA
acky-0.2.3.dist-info/metadata.json
acky-0.2.3.dist-info/RECORD
acky-0.2.3.dist-info/top_level.txt
acky-0.2.3.dist-info/WHEEL
tests/__init__.py
tests/test_ec2.py
tests/test_s3.py
